GoYuyanSishierzhangJing/README.md
GoYuyanSishierzhangJing/__init__.py
GoYuyanSishierzhangJing/__main__.py
GoYuyanSishierzhangJing/file.epub
GoYuyanSishierzhangJing/index.html
GoYuyanSishierzhangJing/css/__init__.py
GoYuyanSishierzhangJing/css/annotations.css
GoYuyanSishierzhangJing/css/main.css
GoYuyanSishierzhangJing/css/normalize.css
GoYuyanSishierzhangJing/css/popup.css
GoYuyanSishierzhangJing/font/__init__.py
GoYuyanSishierzhangJing/font/fontello.eot
GoYuyanSishierzhangJing/font/fontello.svg
GoYuyanSishierzhangJing/font/fontello.ttf
GoYuyanSishierzhangJing/font/fontello.woff
GoYuyanSishierzhangJing/img/__init__.py
GoYuyanSishierzhangJing/img/annotator-glyph-sprite.png
GoYuyanSishierzhangJing/img/annotator-icon-sprite.png
GoYuyanSishierzhangJing/img/apple-touch-icon.png
GoYuyanSishierzhangJing/img/cancelfullscreen.png
GoYuyanSishierzhangJing/img/close.png
GoYuyanSishierzhangJing/img/fullscreen.png
GoYuyanSishierzhangJing/img/loader.gif
GoYuyanSishierzhangJing/img/menu-icon.png
GoYuyanSishierzhangJing/img/save.png
GoYuyanSishierzhangJing/img/saved.png
GoYuyanSishierzhangJing/img/settings-s.png
GoYuyanSishierzhangJing/img/settings.png
GoYuyanSishierzhangJing/img/star.png
GoYuyanSishierzhangJing/js/__init__.py
GoYuyanSishierzhangJing/js/epub.js
GoYuyanSishierzhangJing/js/epub.min.js
GoYuyanSishierzhangJing/js/epub.min.map
GoYuyanSishierzhangJing/js/hooks.min.js
GoYuyanSishierzhangJing/js/hooks.min.map
GoYuyanSishierzhangJing/js/reader.js
GoYuyanSishierzhangJing/js/reader.js.map
GoYuyanSishierzhangJing/js/reader.min.js
GoYuyanSishierzhangJing/js/reader.min.map
GoYuyanSishierzhangJing/js/hooks/__init__.py
GoYuyanSishierzhangJing/js/hooks/extensions/__init__.py
GoYuyanSishierzhangJing/js/hooks/extensions/highlight.js
GoYuyanSishierzhangJing/js/libs/__init__.py
GoYuyanSishierzhangJing/js/libs/jquery.min.js
GoYuyanSishierzhangJing/js/libs/localforage.min.js
GoYuyanSishierzhangJing/js/libs/screenfull.js
GoYuyanSishierzhangJing/js/libs/screenfull.min.js
go_yuyan_sishierzhang_jing-2024.3.5.0.dist-info/METADATA
go_yuyan_sishierzhang_jing-2024.3.5.0.dist-info/WHEEL
go_yuyan_sishierzhang_jing-2024.3.5.0.dist-info/entry_points.txt
go_yuyan_sishierzhang_jing-2024.3.5.0.dist-info/top_level.txt
go_yuyan_sishierzhang_jing-2024.3.5.0.dist-info/RECORD
